kaggle_metrics/__init__.py
kaggle_metrics/classification.py
kaggle_metrics/order_based.py
kaggle_metrics/other.py
kaggle_metrics/regression.py
kaggle_metrics/utils.py
kaggle_metrics-0.3.1.dist-info/METADATA
kaggle_metrics-0.3.1.dist-info/WHEEL
kaggle_metrics-0.3.1.dist-info/top_level.txt
kaggle_metrics-0.3.1.dist-info/RECORD
