Metadata-Version: 2.1
Name: kaggle-metrics
Version: 0.3.1
Summary: Metrics for Kaggle competitions
Home-page: https://github.com/krzjoa/kaggle-metrics
Author: Krzysztof Joachimiak
Author-email: joachimiak.krzysztof@gmail.com
License: UNKNOWN
Keywords: kaggle,metrics
Platform: UNKNOWN
Classifier: Development Status :: 3 - Alpha
Classifier: Topic :: Utilities
